django_spicy_id/__init__.py
django_spicy_id/baseconv.py
django_spicy_id/contrib.py
django_spicy_id/errors.py
django_spicy_id/fields.py
django_spicy_id/utils.py
django_spicy_id-1.0.0.dist-info/LICENSE.txt
django_spicy_id-1.0.0.dist-info/METADATA
django_spicy_id-1.0.0.dist-info/WHEEL
django_spicy_id-1.0.0.dist-info/top_level.txt
django_spicy_id-1.0.0.dist-info/RECORD
