Metadata-Version: 2.1
Name: django-spicy-id
Version: 1.0.0
Summary: Fancy ID fields for django models.
Home-page: https://github.com/mik3y/django-spicy-id
Author: mik3y
Author-email: opensource@hoho.com
License: MIT
Keywords: django timeseries
Platform: any
Classifier: Development Status :: 5 - Production/Stable
Classifier: Framework :: Django
Classifier: Framework :: Django :: 2.2
Classifier: Framework :: Django :: 3.0
Classifier: Framework :: Django :: 4.0
Classifier: Framework :: Django :: 4.1
Classifier: Intended Audience :: Developers
Classifier: License :: OSI Approved :: MIT License
Classifier: Operating System :: OS Independent
Classifier: Programming Language :: Python :: 3
Classifier: Programming Language :: Python :: 3.9
Classifier: Programming Language :: Python :: 3.10
Classifier: Programming Language :: Python :: 3.11
Classifier: Programming Language :: Python :: 3.12
Classifier: Programming Language :: Python :: 3 :: Only
Requires-Python: >=3.9.0
License-File: LICENSE.txt
Requires-Dist: Django >=2.2
